{
  "job": 1,
  "projectId": 1,
  "runId": 2,
  "state": "success",
  "exactMatch": true,
  "runCase": {
    "questionId": 1,
    "dbId": "academic",
    "dataset": "spider",
    "hostOrPath": "/workspace/src/flask/static/spider/academic.sqlite",
    "gold": "SELECT name FROM students",
    "pred": "SELECT name FROM students"
  },
  "resultsBySettings": {
    "db=NONE|query=SET": {
      "state": "equivalent",
      "dbLevel": "NONE",
      "queryLevel": "SET",
      "witnessDb": null,
      "q1Result": {
        "query": "SELECT name FROM students",
        "host_or_path": "/workspace/src/flask/static/spider/academic.sqlite",
        "db_id": "academic",
        "question_id": 1,
        "dataset": "spider",
        "dialect": "sqlite",
        "elapsed_time": 0,
        "rows": [],
        "columns": [],
        "error_msg": ""
      },
      "q2Result": {
        "query": "SELECT name FROM students",
        "host_or_path": "/workspace/src/flask/static/spider/academic.sqlite",
        "db_id": "academic",
        "question_id": 1,
        "dataset": "spider",
        "dialect": "sqlite",
        "elapsed_time": 0,
        "rows": [],
        "columns": [],
        "error_msg": ""
      }
    },
    "db=NONE|query=BAG": {
      "state": "equivalent",
      "dbLevel": "NONE",
      "queryLevel": "BAG",
      "witnessDb": null,
      "q1Result": {
        "query": "SELECT name FROM students",
        "host_or_path": "/workspace/src/flask/static/spider/academic.sqlite",
        "db_id": "academic",
        "question_id": 1,
        "dataset": "spider",
        "dialect": "sqlite",
        "elapsed_time": 0,
        "rows": [],
        "columns": [],
        "error_msg": ""
      },
      "q2Result": {
        "query": "SELECT name FROM students",
        "host_or_path": "/workspace/src/flask/static/spider/academic.sqlite",
        "db_id": "academic",
        "question_id": 1,
        "dataset": "spider",
        "dialect": "sqlite",
        "elapsed_time": 0,
        "rows": [],
        "columns": [],
        "error_msg": ""
      }
    },
    "db=PK_FK|query=SET": {
      "state": "equivalent",
      "dbLevel": "PK_FK",
      "queryLevel": "SET",
      "witnessDb": null,
      "q1Result": {
        "query": "SELECT name FROM students",
        "host_or_path": "/workspace/src/flask/static/spider/academic.sqlite",
        "db_id": "academic",
        "question_id": 1,
        "dataset": "spider",
        "dialect": "sqlite",
        "elapsed_time": 0,
        "rows": [],
        "columns": [],
        "error_msg": ""
      },
      "q2Result": {
        "query": "SELECT name FROM students",
        "host_or_path": "/workspace/src/flask/static/spider/academic.sqlite",
        "db_id": "academic",
        "question_id": 1,
        "dataset": "spider",
        "dialect": "sqlite",
        "elapsed_time": 0,
        "rows": [],
        "columns": [],
        "error_msg": ""
      }
    },
    "db=PK_FK|query=BAG": {
      "state": "equivalent",
      "dbLevel": "PK_FK",
      "queryLevel": "BAG",
      "witnessDb": null,
      "q1Result": {
        "query": "SELECT name FROM students",
        "host_or_path": "/workspace/src/flask/static/spider/academic.sqlite",
        "db_id": "academic",
        "question_id": 1,
        "dataset": "spider",
        "dialect": "sqlite",
        "elapsed_time": 0,
        "rows": [],
        "columns": [],
        "error_msg": ""
      },
      "q2Result": {
        "query": "SELECT name FROM students",
        "host_or_path": "/workspace/src/flask/static/spider/academic.sqlite",
        "db_id": "academic",
        "question_id": 1,
        "dataset": "spider",
        "dialect": "sqlite",
        "elapsed_time": 0,
        "rows": [],
        "columns": [],
        "error_msg": ""
      }
    },
    "db=PK_FK_NULL|query=SET": {
      "state": "equivalent",
      "dbLevel": "PK_FK_NULL",
      "queryLevel": "SET",
      "witnessDb": null,
      "q1Result": {
        "query": "SELECT name FROM students",
        "host_or_path": "/workspace/src/flask/static/spider/academic.sqlite",
        "db_id": "academic",
        "question_id": 1,
        "dataset": "spider",
        "dialect": "sqlite",
        "elapsed_time": 0,
        "rows": [],
        "columns": [],
        "error_msg": ""
      },
      "q2Result": {
        "query": "SELECT name FROM students",
        "host_or_path": "/workspace/src/flask/static/spider/academic.sqlite",
        "db_id": "academic",
        "question_id": 1,
        "dataset": "spider",
        "dialect": "sqlite",
        "elapsed_time": 0,
        "rows": [],
        "columns": [],
        "error_msg": ""
      }
    },
    "db=PK_FK_NULL|query=BAG": {
      "state": "equivalent",
      "dbLevel": "PK_FK_NULL",
      "queryLevel": "BAG",
      "witnessDb": null,
      "q1Result": {
        "query": "SELECT name FROM students",
        "host_or_path": "/workspace/src/flask/static/spider/academic.sqlite",
        "db_id": "academic",
        "question_id": 1,
        "dataset": "spider",
        "dialect": "sqlite",
        "elapsed_time": 0,
        "rows": [],
        "columns": [],
        "error_msg": ""
      },
      "q2Result": {
        "query": "SELECT name FROM students",
        "host_or_path": "/workspace/src/flask/static/spider/academic.sqlite",
        "db_id": "academic",
        "question_id": 1,
        "dataset": "spider",
        "dialect": "sqlite",
        "elapsed_time": 0,
        "rows": [],
        "columns": [],
        "error_msg": ""
      }
    },
    "db=FULL|query=SET": {
      "state": "equivalent",
      "dbLevel": "FULL",
      "queryLevel": "SET",
      "witnessDb": null,
      "q1Result": {
        "query": "SELECT name FROM students",
        "host_or_path": "/workspace/src/flask/static/spider/academic.sqlite",
        "db_id": "academic",
        "question_id": 1,
        "dataset": "spider",
        "dialect": "sqlite",
        "elapsed_time": 0,
        "rows": [],
        "columns": [],
        "error_msg": ""
      },
      "q2Result": {
        "query": "SELECT name FROM students",
        "host_or_path": "/workspace/src/flask/static/spider/academic.sqlite",
        "db_id": "academic",
        "question_id": 1,
        "dataset": "spider",
        "dialect": "sqlite",
        "elapsed_time": 0,
        "rows": [],
        "columns": [],
        "error_msg": ""
      }
    },
    "db=FULL|query=BAG": {
      "state": "equivalent",
      "dbLevel": "FULL",
      "queryLevel": "BAG",
      "witnessDb": null,
      "q1Result": {
        "query": "SELECT name FROM students",
        "host_or_path": "/workspace/src/flask/static/spider/academic.sqlite",
        "db_id": "academic",
        "question_id": 1,
        "dataset": "spider",
        "dialect": "sqlite",
        "elapsed_time": 0,
        "rows": [],
        "columns": [],
        "error_msg": ""
      },
      "q2Result": {
        "query": "SELECT name FROM students",
        "host_or_path": "/workspace/src/flask/static/spider/academic.sqlite",
        "db_id": "academic",
        "question_id": 1,
        "dataset": "spider",
        "dialect": "sqlite",
        "elapsed_time": 0,
        "rows": [],
        "columns": [],
        "error_msg": ""
      }
    }
  },
  "levels": [
    {
      "settingKey": "db=NONE|query=SET",
      "dbLevel": "NONE",
      "queryLevel": "SET",
      "state": "equivalent",
      "witnessDb": null,
      "q1Result": {
        "query": "SELECT name FROM students",
        "host_or_path": "/workspace/src/flask/static/spider/academic.sqlite",
        "db_id": "academic",
        "question_id": 1,
        "dataset": "spider",
        "dialect": "sqlite",
        "elapsed_time": 0,
        "rows": [],
        "columns": [],
        "error_msg": ""
      },
      "q2Result": {
        "query": "SELECT name FROM students",
        "host_or_path": "/workspace/src/flask/static/spider/academic.sqlite",
        "db_id": "academic",
        "question_id": 1,
        "dataset": "spider",
        "dialect": "sqlite",
        "elapsed_time": 0,
        "rows": [],
        "columns": [],
        "error_msg": ""
      }
    },
    {
      "settingKey": "db=NONE|query=BAG",
      "dbLevel": "NONE",
      "queryLevel": "BAG",
      "state": "equivalent",
      "witnessDb": null,
      "q1Result": {
        "query": "SELECT name FROM students",
        "host_or_path": "/workspace/src/flask/static/spider/academic.sqlite",
        "db_id": "academic",
        "question_id": 1,
        "dataset": "spider",
        "dialect": "sqlite",
        "elapsed_time": 0,
        "rows": [],
        "columns": [],
        "error_msg": ""
      },
      "q2Result": {
        "query": "SELECT name FROM students",
        "host_or_path": "/workspace/src/flask/static/spider/academic.sqlite",
        "db_id": "academic",
        "question_id": 1,
        "dataset": "spider",
        "dialect": "sqlite",
        "elapsed_time": 0,
        "rows": [],
        "columns": [],
        "error_msg": ""
      }
    },
    {
      "settingKey": "db=PK_FK|query=SET",
      "dbLevel": "PK_FK",
      "queryLevel": "SET",
      "state": "equivalent",
      "witnessDb": null,
      "q1Result": {
        "query": "SELECT name FROM students",
        "host_or_path": "/workspace/src/flask/static/spider/academic.sqlite",
        "db_id": "academic",
        "question_id": 1,
        "dataset": "spider",
        "dialect": "sqlite",
        "elapsed_time": 0,
        "rows": [],
        "columns": [],
        "error_msg": ""
      },
      "q2Result": {
        "query": "SELECT name FROM students",
        "host_or_path": "/workspace/src/flask/static/spider/academic.sqlite",
        "db_id": "academic",
        "question_id": 1,
        "dataset": "spider",
        "dialect": "sqlite",
        "elapsed_time": 0,
        "rows": [],
        "columns": [],
        "error_msg": ""
      }
    },
    {
      "settingKey": "db=PK_FK|query=BAG",
      "dbLevel": "PK_FK",
      "queryLevel": "BAG",
      "state": "equivalent",
      "witnessDb": null,
      "q1Result": {
        "query": "SELECT name FROM students",
        "host_or_path": "/workspace/src/flask/static/spider/academic.sqlite",
        "db_id": "academic",
        "question_id": 1,
        "dataset": "spider",
        "dialect": "sqlite",
        "elapsed_time": 0,
        "rows": [],
        "columns": [],
        "error_msg": ""
      },
      "q2Result": {
        "query": "SELECT name FROM students",
        "host_or_path": "/workspace/src/flask/static/spider/academic.sqlite",
        "db_id": "academic",
        "question_id": 1,
        "dataset": "spider",
        "dialect": "sqlite",
        "elapsed_time": 0,
        "rows": [],
        "columns": [],
        "error_msg": ""
      }
    },
    {
      "settingKey": "db=PK_FK_NULL|query=SET",
      "dbLevel": "PK_FK_NULL",
      "queryLevel": "SET",
      "state": "equivalent",
      "witnessDb": null,
      "q1Result": {
        "query": "SELECT name FROM students",
        "host_or_path": "/workspace/src/flask/static/spider/academic.sqlite",
        "db_id": "academic",
        "question_id": 1,
        "dataset": "spider",
        "dialect": "sqlite",
        "elapsed_time": 0,
        "rows": [],
        "columns": [],
        "error_msg": ""
      },
      "q2Result": {
        "query": "SELECT name FROM students",
        "host_or_path": "/workspace/src/flask/static/spider/academic.sqlite",
        "db_id": "academic",
        "question_id": 1,
        "dataset": "spider",
        "dialect": "sqlite",
        "elapsed_time": 0,
        "rows": [],
        "columns": [],
        "error_msg": ""
      }
    },
    {
      "settingKey": "db=PK_FK_NULL|query=BAG",
      "dbLevel": "PK_FK_NULL",
      "queryLevel": "BAG",
      "state": "equivalent",
      "witnessDb": null,
      "q1Result": {
        "query": "SELECT name FROM students",
        "host_or_path": "/workspace/src/flask/static/spider/academic.sqlite",
        "db_id": "academic",
        "question_id": 1,
        "dataset": "spider",
        "dialect": "sqlite",
        "elapsed_time": 0,
        "rows": [],
        "columns": [],
        "error_msg": ""
      },
      "q2Result": {
        "query": "SELECT name FROM students",
        "host_or_path": "/workspace/src/flask/static/spider/academic.sqlite",
        "db_id": "academic",
        "question_id": 1,
        "dataset": "spider",
        "dialect": "sqlite",
        "elapsed_time": 0,
        "rows": [],
        "columns": [],
        "error_msg": ""
      }
    },
    {
      "settingKey": "db=FULL|query=SET",
      "dbLevel": "FULL",
      "queryLevel": "SET",
      "state": "equivalent",
      "witnessDb": null,
      "q1Result": {
        "query": "SELECT name FROM students",
        "host_or_path": "/workspace/src/flask/static/spider/academic.sqlite",
        "db_id": "academic",
        "question_id": 1,
        "dataset": "spider",
        "dialect": "sqlite",
        "elapsed_time": 0,
        "rows": [],
        "columns": [],
        "error_msg": ""
      },
      "q2Result": {
        "query": "SELECT name FROM students",
        "host_or_path": "/workspace/src/flask/static/spider/academic.sqlite",
        "db_id": "academic",
        "question_id": 1,
        "dataset": "spider",
        "dialect": "sqlite",
        "elapsed_time": 0,
        "rows": [],
        "columns": [],
        "error_msg": ""
      }
    },
    {
      "settingKey": "db=FULL|query=BAG",
      "dbLevel": "FULL",
      "queryLevel": "BAG",
      "state": "equivalent",
      "witnessDb": null,
      "q1Result": {
        "query": "SELECT name FROM students",
        "host_or_path": "/workspace/src/flask/static/spider/academic.sqlite",
        "db_id": "academic",
        "question_id": 1,
        "dataset": "spider",
        "dialect": "sqlite",
        "elapsed_time": 0,
        "rows": [],
        "columns": [],
        "error_msg": ""
      },
      "q2Result": {
        "query": "SELECT name FROM students",
        "host_or_path": "/workspace/src/flask/static/spider/academic.sqlite",
        "db_id": "academic",
        "question_id": 1,
        "dataset": "spider",
        "dialect": "sqlite",
        "elapsed_time": 0,
        "rows": [],
        "columns": [],
        "error_msg": ""
      }
    }
  ]
}
